[
    {
        "id": 1,
        "imgSrc": "california-hit.jpg",
        "title": "Каліфорнія хіт рол",
        "portionText": "В одній порції",
        "itemsInBox": 6,
        "weight":180,
        "price":105,
        "buttonText": "до кошика"
    },
    {
        "id": 2,
        "imgSrc": "california-tempura.jpg",
        "title": "Каліфорнія Темпура",
        "portionText": "В одній порції",
        "itemsInBox": 6,
        "weight":205,
        "price":145,
        "buttonText": "до кошика"
    },
    {
        "id": 3,
        "imgSrc": "zapech-california.jpg",
        "title": "Запечений рол «Каліфорнія»",
        "portionText": "В одній порції",
        "itemsInBox": 6,
        "weight":182,
        "price":130,
        "buttonText": "до кошика"
    },
    {
        "id": 4,
        "imgSrc": "philadelphia.jpg",
        "title": "Філадельфія рол",
        "portionText": "В одній порції",
        "itemsInBox": 6,
        "weight":230,
        "price":125,
        "buttonText": "до кошика"
    }
]